setup.py
json/__init__.py
json/decoder.py
json/encoder.py
json/scanner.py
json/tool.py
micropython_json.egg-info/PKG-INFO
micropython_json.egg-info/SOURCES.txt
micropython_json.egg-info/dependency_links.txt
micropython_json.egg-info/requires.txt
micropython_json.egg-info/top_level.txt